setup.py
example_package_YG_HERE/__init__.py
example_package_YG_HERE/example.py
example_package_YG_HERE.egg-info/PKG-INFO
example_package_YG_HERE.egg-info/SOURCES.txt
example_package_YG_HERE.egg-info/dependency_links.txt
example_package_YG_HERE.egg-info/top_level.txt