Metadata-Version: 1.1
Name: example-package-YG-HERE
Version: 1.1.3
Summary: a package for your test using
Home-page: https://github.com/boss2020/tfbert
Author: yingang
Author-email: 474551240@qq.com
License: Apache License 2.0
Download-URL: https://github.com/boss2020/tfbert/master.zip
Platform: UNKNOWN
